Metadata-Version: 1.1
Name: whitepy
Version: 0.4
Summary: Whitespace interpreter written in Python 3
Home-page: https://github.com/yasn77/whitepy
Author: Yasser Nabi
Author-email: yassersaleemi@gmail.com
License: LICENSE.txt
Download-URL: https://github.com/yasn77/whitepy/archive/0.4.tar.gz
Platform: UNKNOWN
